stuzha/AMT.py
stuzha/AoA.py
stuzha/CIS.py
stuzha/ML.py
stuzha/__init__.py
stuzha-0.2.1.dist-info/METADATA
stuzha-0.2.1.dist-info/WHEEL
stuzha-0.2.1.dist-info/entry_points.txt
stuzha-0.2.1.dist-info/top_level.txt
stuzha-0.2.1.dist-info/RECORD
