Metadata-Version: 2.4
Name: stuzha
Version: 0.2.1
Requires-Dist: colorama>=0.4.6
Dynamic: requires-dist
